easy_logging_config-1.0.0.dist-info/METADATA
easy_logging_config-1.0.0.dist-info/RECORD
easy_logging_config-1.0.0.dist-info/WHEEL
easy_logging_config-1.0.0.dist-info/top_level.txt
logging_config/__init__.py
logging_config/constants.py
logging_config/log_configuration.py
logging_config/version.py
logging_config/components/__init__.py
logging_config/components/default_logging_components.py
logging_config/components/filters.py
logging_config/components/formatter.py
