Metadata-Version: 2.1
Name: easy-logging-config
Version: 1.0.0
Summary: An easy to use logging library
Home-page: https://github.com/Surbhi-1206/easy_logging_config
Author: Surbhi Saraogi
Author-email: surbhi.saraogi95@gmail.com
License: MIT
Platform: UNKNOWN
Classifier: Programming Language :: Python :: 3
Classifier: License :: OSI Approved :: MIT License
Classifier: Operating System :: OS Independent
Requires-Dist: logstash-formatter
